pixsdk/__init__.py
pixsdk/__main__.py
pixsdk/cli.py
pixsdk/context.py
pixsdk/engine.py
pixsdk/git.py
pixsdk/plugin.py
pixsdk/plugins/__init__.py
pixsdk/plugins/config.py
pixsdk/plugins/core.py
pixsdk/plugins/fetch.py
pixsdk/plugins/github.py
pixsdk/plugins/log.py
pixsdk/plugins/pixie.py
pixsdk/plugins/shell.py
pixsdk/rendering.py
pixsdk/runtime.py
pixsdk/steps.py
pixsdk/utils.py
pixsdk-0.0.2.dist-info/entry_points.txt
pixsdk-0.0.2.dist-info/WHEEL
pixsdk-0.0.2.dist-info/METADATA
pixsdk-0.0.2.dist-info/RECORD
